setup.cfg
setup.py
django_template_finder_view/__init__.py
django_template_finder_view.egg-info/PKG-INFO
django_template_finder_view.egg-info/SOURCES.txt
django_template_finder_view.egg-info/dependency_links.txt
django_template_finder_view.egg-info/requires.txt
django_template_finder_view.egg-info/top_level.txt