Metadata-Version: 1.0
Name: django-template-finder-view
Version: 0.2
Summary: A view for automatically finding and rendering Django templates
Home-page: UNKNOWN
Author: Robin
Author-email: UNKNOWN
License: LGPLv3
Platform: any
